{
  "project_info": {
    "project_number": "976999810599",
    "firebase_url": "https://bmco-99423.firebaseio.com",
    "project_id": "bmco-99423",
    "storage_bucket": "bmco-99423.appspot.com"
  },
  "client": [
    {
      "client_info": {
        "mobilesdk_app_id": "1:976999810599:android:e88ecb26d8fbdb40",
        "android_client_info": {
          "package_name": "com.example.track"
        }
      },
      "oauth_client": [
        {
          "client_id": "976999810599-phdvsi8kghq1fafh66lpdnldq1oke6iq.apps.googleusercontent.com",
          "client_type": 3
        }
      ],
      "api_key": [
        {
          "current_key": "AIzaSyBtHmBGExBDizFyUAxLXBworiRhqr3vOKk"
        }
      ],
      "services": {
        "appinvite_service": {
          "other_platform_oauth_client": [
            {
              "client_id": "976999810599-phdvsi8kghq1fafh66lpdnldq1oke6iq.apps.googleusercontent.com",
              "client_type": 3
            }
          ]
        }
      }
    }
  ],
  "configuration_version": "1"
}